mindbridgeapi/__init__.py
mindbridgeapi/account_group_item.py
mindbridgeapi/account_grouping_item.py
mindbridgeapi/account_groupings.py
mindbridgeapi/account_groups.py
mindbridgeapi/account_mapping_item.py
mindbridgeapi/account_mappings.py
mindbridgeapi/accounting_period.py
mindbridgeapi/activity_report_parameters.py
mindbridgeapi/admin_reports.py
mindbridgeapi/analyses.py
mindbridgeapi/analysis_item.py
mindbridgeapi/analysis_period.py
mindbridgeapi/analysis_result_item.py
mindbridgeapi/analysis_results.py
mindbridgeapi/analysis_source_item.py
mindbridgeapi/analysis_source_type_item.py
mindbridgeapi/analysis_source_types.py
mindbridgeapi/analysis_sources.py
mindbridgeapi/analysis_type_configuration_item.py
mindbridgeapi/analysis_type_configurations.py
mindbridgeapi/analysis_type_item.py
mindbridgeapi/analysis_types.py
mindbridgeapi/api_token_item.py
mindbridgeapi/api_tokens.py
mindbridgeapi/async_result_item.py
mindbridgeapi/async_results.py
mindbridgeapi/base_set.py
mindbridgeapi/chunked_file_item.py
mindbridgeapi/chunked_file_part_item.py
mindbridgeapi/chunked_files.py
mindbridgeapi/column_mapping.py
mindbridgeapi/common_validators.py
mindbridgeapi/data_tables.py
mindbridgeapi/engagement_account_group_item.py
mindbridgeapi/engagement_account_grouping_item.py
mindbridgeapi/engagement_account_groupings.py
mindbridgeapi/engagement_account_groups.py
mindbridgeapi/engagement_item.py
mindbridgeapi/engagements.py
mindbridgeapi/exceptions.py
mindbridgeapi/file_info_item.py
mindbridgeapi/file_infos.py
mindbridgeapi/file_manager.py
mindbridgeapi/file_manager_item.py
mindbridgeapi/file_result_item.py
mindbridgeapi/file_results.py
mindbridgeapi/filter_group_condition_item.py
mindbridgeapi/json_tables.py
mindbridgeapi/libraries.py
mindbridgeapi/library_item.py
mindbridgeapi/organization_item.py
mindbridgeapi/organizations.py
mindbridgeapi/population_item.py
mindbridgeapi/populations.py
mindbridgeapi/py.typed
mindbridgeapi/risk_ranges.py
mindbridgeapi/risk_ranges_item.py
mindbridge_api_python_client-1.8.3.dist-info/METADATA
mindbridge_api_python_client-1.8.3.dist-info/WHEEL
mindbridge_api_python_client-1.8.3.dist-info/licenses/LICENSE.txt
mindbridge_api_python_client-1.8.3.dist-info/RECORD
