Metadata-Version: 2.4
Name: mindbridge-api-python-client
Version: 1.8.3
Summary: Interact with the MindBridge API
Project-URL: Homepage, https://www.mindbridge.ai
Author-email: MBAI Support <mbaisupport@mindbridge.ai>
Maintainer-email: MBAI Support <mbaisupport@mindbridge.ai>
License-Expression: LicenseRef-Proprietary
License-File: LICENSE.txt
Keywords: MindBridge
Classifier: Development Status :: 4 - Beta
Classifier: Operating System :: OS Independent
Classifier: Programming Language :: Python :: 3 :: Only
Classifier: Programming Language :: Python :: 3.10
Classifier: Programming Language :: Python :: 3.11
Classifier: Programming Language :: Python :: 3.12
Classifier: Programming Language :: Python :: 3.13
Classifier: Programming Language :: Python :: 3.14
Classifier: Typing :: Typed
Requires-Python: >=3.10
Requires-Dist: annotated-types>=0.6.0
Requires-Dist: pydantic<=2.12.5,>=2.10.4
Requires-Dist: urllib3<=2.6.1,>=2.6.0
